{"page_id": "444222", "page_title": "Narendra Modi", "utc_time_now_string": "2022-07-29T18:30:00Z", "pagerevisions_list": [{"revid": 1099586404, "parentid": 1099586181, "user": "Sahil193319", "userid": 41930271, "timestamp": "2022-07-21T15:11:39Z", "size": 310468, "tags": ["mobile edit", "mobile web edit", "mw-reverted"]}, {"revid": 1098977356, "parentid": 1098363538, "user": "Sahil193319", "userid": 41930271, "timestamp": "2022-07-18T11:12:53Z", "size": 310461, "tags": ["mobile edit", "mobile web edit", "mw-reverted"]}]}